{"id":"pxskxjbb6bdjeqfkpxfuschwn7nzsn4pefntiufrjxolzp5bygoq","stamp":"2024-03-05T22:44:31.15036332Z","payload":{"op":"motion_close","note":"","args":{"id":"26"},"result":{"motion":{"opened_at":"2024-03-05T22:37:46.176117691Z","closed_at":"2024-03-05T22:44:31.146616906Z","id":"26","type":"proposal","policy":"waimea-proposal","author":"petar","tracker_url":"https://github.com/gov4git/sample-project/pull/26","title":"Create LICENSE","description":"I've added a reasonable license.\r\n\r\nIssues that this PR claims:\r\n- claims https://github.com/gov4git/sample-project/issues/25","labels":["gov4git:managed"],"frozen":false,"closed":true,"cancelled":false,"archived":false,"score":{"attention":6},"ref_by":null,"ref_to":[{"type":"claims","from":"26","to":"25"}]}}}}
